autoagents/__init__.py
autoagents/agent_wrapper.py
autoagents/autonomous_agent.py
autoagents/dummy_agent.py
autoagents/human_agent.py
autoagents/npc_agent.py
autoagents/ros_agent.py
autoagents/sensor_interface.py
scenarioconfigs/__init__.py
scenarioconfigs/openscenario_configuration.py
scenarioconfigs/route_scenario_configuration.py
scenarioconfigs/scenario_configuration.py
scenariomanager/__init__.py
scenariomanager/carla_data_provider.py
scenariomanager/result_writer.py
scenariomanager/scenario_manager.py
scenariomanager/timer.py
scenariomanager/traffic_events.py
scenariomanager/watchdog.py
scenariomanager/weather_sim.py
scenariomanager/actorcontrols/__init__.py
scenariomanager/actorcontrols/actor_control.py
scenariomanager/actorcontrols/basic_control.py
scenariomanager/actorcontrols/carla_autopilot.py
scenariomanager/actorcontrols/external_control.py
scenariomanager/actorcontrols/npc_vehicle_control.py
scenariomanager/actorcontrols/pedestrian_control.py
scenariomanager/actorcontrols/simple_vehicle_control.py
scenariomanager/actorcontrols/vehicle_longitudinal_control.py
scenariomanager/actorcontrols/visualizer.py
scenariomanager/scenarioatomics/__init__.py
scenariomanager/scenarioatomics/atomic_behaviors.py
scenariomanager/scenarioatomics/atomic_criteria.py
scenariomanager/scenarioatomics/atomic_trigger_conditions.py
scenarios/__init__.py
scenarios/background_activity.py
scenarios/basic_scenario.py
scenarios/change_lane.py
scenarios/construction_crash_vehicle.py
scenarios/control_loss.py
scenarios/cut_in.py
scenarios/follow_leading_vehicle.py
scenarios/freeride.py
scenarios/junction_crossing_route.py
scenarios/maneuver_opposite_direction.py
scenarios/master_scenario.py
scenarios/no_signal_junction_crossing.py
scenarios/object_crash_intersection.py
scenarios/object_crash_vehicle.py
scenarios/open_scenario.py
scenarios/opposite_vehicle_taking_priority.py
scenarios/other_leading_vehicle.py
scenarios/route_scenario.py
scenarios/signalized_junction_left_turn.py
carla_scenario_runner-0.9.11.dist-info/LICENSE
carla_scenario_runner-0.9.11.dist-info/METADATA
carla_scenario_runner-0.9.11.dist-info/WHEEL
carla_scenario_runner-0.9.11.dist-info/top_level.txt
carla_scenario_runner-0.9.11.dist-info/RECORD
