Metadata-Version: 2.1
Name: carla-scenario-runner
Version: 0.9.11
Summary: Scenario runner for CARLA
Home-page: https://github.com/carla-simulator/scenario_runner
Author: CARLA Simulator Team
Author-email: contact@function-t.tech
License: UNKNOWN
Project-URL: Bug Tracker, https://github.com/carla-simulator/scenario_runner/issues
Platform: UNKNOWN
Classifier: Programming Language :: Python :: 3
Classifier: License :: OSI Approved :: MIT License
Classifier: Operating System :: OS Independent
Requires-Python: >=3.6
